CHANGELOG.md
LICENSE
django_web_components/__init__.py
django_web_components/attributes.py
django_web_components/component.py
django_web_components/conf.py
django_web_components/registry.py
django_web_components/tag_formatter.py
django_web_components/template.py
django_web_components/templatetags/__init__.py
django_web_components/templatetags/components.py
django_web_components/utils.py
django_web_components-0.2.0.dist-info/LICENSE
django_web_components-0.2.0.dist-info/METADATA
django_web_components-0.2.0.dist-info/WHEEL
django_web_components-0.2.0.dist-info/RECORD
