Metadata-Version: 2.1
Name: django-web-components
Version: 0.2.0
Summary: Build reusable template components in Django
Home-page: https://github.com/Xzya/django-web-components
License: MIT
Keywords: django,components
Author: Mihail Cristian Dumitru
Requires-Python: >=3.8,<4.0
Classifier: Development Status :: 3 - Alpha
Classifier: Environment :: Web Environment
Classifier: Framework :: Django
Classifier: Framework :: Django :: 3.2
Classifier: Framework :: Django :: 4.0
Classifier: Framework :: Django :: 4.1
Classifier: License :: OSI Approved :: MIT License
Classifier: Operating System :: OS Independent
Classifier: Programming Language :: Python :: 3
Classifier: Programming Language :: Python :: 3.8
Classifier: Programming Language :: Python :: 3.9
Classifier: Programming Language :: Python :: 3.10
Classifier: Programming Language :: Python :: 3.11
Requires-Dist: Django (>=3.2)
Project-URL: Repository, https://github.com/Xzya/django-web-components
